digitalhub_runtime_hera/__init__.py
digitalhub_runtime_hera/dsl.py
digitalhub_runtime_hera/entities/__init__.py
digitalhub_runtime_hera/entities/_base/__init__.py
digitalhub_runtime_hera/entities/_base/runtime_entity/__init__.py
digitalhub_runtime_hera/entities/_base/runtime_entity/builder.py
digitalhub_runtime_hera/entities/_commons/__init__.py
digitalhub_runtime_hera/entities/_commons/enums.py
digitalhub_runtime_hera/entities/run/__init__.py
digitalhub_runtime_hera/entities/run/_base/__init__.py
digitalhub_runtime_hera/entities/run/_base/entity.py
digitalhub_runtime_hera/entities/run/_base/spec.py
digitalhub_runtime_hera/entities/run/_base/status.py
digitalhub_runtime_hera/entities/run/build/__init__.py
digitalhub_runtime_hera/entities/run/build/builder.py
digitalhub_runtime_hera/entities/run/build/entity.py
digitalhub_runtime_hera/entities/run/build/spec.py
digitalhub_runtime_hera/entities/run/build/status.py
digitalhub_runtime_hera/entities/run/pipeline/__init__.py
digitalhub_runtime_hera/entities/run/pipeline/builder.py
digitalhub_runtime_hera/entities/run/pipeline/entity.py
digitalhub_runtime_hera/entities/run/pipeline/spec.py
digitalhub_runtime_hera/entities/run/pipeline/status.py
digitalhub_runtime_hera/entities/task/__init__.py
digitalhub_runtime_hera/entities/task/build/__init__.py
digitalhub_runtime_hera/entities/task/build/builder.py
digitalhub_runtime_hera/entities/task/build/entity.py
digitalhub_runtime_hera/entities/task/build/spec.py
digitalhub_runtime_hera/entities/task/build/status.py
digitalhub_runtime_hera/entities/task/pipeline/__init__.py
digitalhub_runtime_hera/entities/task/pipeline/builder.py
digitalhub_runtime_hera/entities/task/pipeline/entity.py
digitalhub_runtime_hera/entities/task/pipeline/spec.py
digitalhub_runtime_hera/entities/task/pipeline/status.py
digitalhub_runtime_hera/entities/workflow/__init__.py
digitalhub_runtime_hera/entities/workflow/hera/__init__.py
digitalhub_runtime_hera/entities/workflow/hera/builder.py
digitalhub_runtime_hera-0.14.0.dist-info/METADATA
digitalhub_runtime_hera-0.14.0.dist-info/WHEEL
digitalhub_runtime_hera-0.14.0.dist-info/licenses/AUTHORS
digitalhub_runtime_hera-0.14.0.dist-info/licenses/LICENSE
digitalhub_runtime_hera-0.14.0.dist-info/RECORD
